edipack2py/__init__.py
edipack2py/class_creator.py
edipack2py/func_aux_funx.py
edipack2py/func_bath.py
edipack2py/func_bath_fit.py
edipack2py/func_io.py
edipack2py/func_main.py
edipack2py/func_parse_umatrix.py
edipack2py/func_read_input.py
edipack2py-5.4.2.dist-info/licenses/LICENSE.txt
edipack2py-5.4.2.dist-info/METADATA
edipack2py-5.4.2.dist-info/WHEEL
edipack2py-5.4.2.dist-info/top_level.txt
edipack2py-5.4.2.dist-info/RECORD
